[
  {
    "id": "PASSENGER-9839",
    "name": "Carla Lindgren",
    "phone": "672.364.3173 x8773"
  },
  {
    "id": "PASSENGER-2640",
    "name": "Debbie Mayert",
    "phone": "1-720-298-6608 x3742"
  },
  {
    "id": "PASSENGER-1866",
    "name": "Grady Halvorson-Corkery",
    "phone": "783-722-7564"
  },
  {
    "id": "PASSENGER-7160",
    "name": "Dr. Edwin Altenwerth",
    "phone": "(212) 665-8723 x22124"
  },
  {
    "id": "PASSENGER-5748",
    "name": "Salvador Ondricka",
    "phone": "222.425.2542 x4955"
  },
  {
    "id": "PASSENGER-4829",
    "name": "Jason Maggio",
    "phone": "717-934-4566 x47382"
  },
  {
    "id": "PASSENGER-5359",
    "name": "Ms. Candace Kozey",
    "phone": "(713) 350-4961 x4632"
  },
  {
    "id": "PASSENGER-2830",
    "name": "Grady Cummerata",
    "phone": "(481) 805-3188"
  },
  {
    "id": "PASSENGER-4246",
    "name": "Darryl Willms",
    "phone": "908.803.6869 x059"
  },
  {
    "id": "PASSENGER-2987",
    "name": "Ricky Ziemann",
    "phone": "1-751-671-8969 x6112"
  },
  {
    "id": "PASSENGER-2108",
    "name": "Andrew Kuhn",
    "phone": "(700) 343-4522"
  },
  {
    "id": "PASSENGER-5472",
    "name": "Mr. Sammy Nienow",
    "phone": "(851) 810-0299 x527"
  },
  {
    "id": "PASSENGER-4320",
    "name": "Dorothy Rogahn-Gleason",
    "phone": "1-536-825-8182 x1418"
  },
  {
    "id": "PASSENGER-3799",
    "name": "Veronica Boyer",
    "phone": "(600) 309-3949 x85975"
  },
  {
    "id": "PASSENGER-8005",
    "name": "Stacy Boehm",
    "phone": "897.269.5808 x0288"
  },
  {
    "id": "PASSENGER-8361",
    "name": "Shelia Becker",
    "phone": "236.341.8602 x39600"
  },
  {
    "id": "PASSENGER-4519",
    "name": "Florence Beatty",
    "phone": "(979) 777-1800 x2960"
  },
  {
    "id": "PASSENGER-8034",
    "name": "Tanya Streich-Brekke",
    "phone": "938.484.8881 x25683"
  },
  {
    "id": "PASSENGER-3039",
    "name": "Susie Hoeger",
    "phone": "1-573-696-5588 x178"
  },
  {
    "id": "PASSENGER-7986",
    "name": "Roman Dare MD",
    "phone": "1-407-268-8853 x401"
  },
  {
    "id": "PASSENGER-9106",
    "name": "William Ullrich",
    "phone": "891-268-8544 x94390"
  },
  {
    "id": "PASSENGER-5852",
    "name": "Gwendolyn Moore",
    "phone": "1-654-901-4276 x548"
  },
  {
    "id": "PASSENGER-9474",
    "name": "Mr. Andre Huels",
    "phone": "1-322-281-5711 x16994"
  },
  {
    "id": "PASSENGER-2771",
    "name": "Stuart Bashirian",
    "phone": "1-915-295-4366 x899"
  },
  {
    "id": "PASSENGER-1976",
    "name": "Rafael O'Hara",
    "phone": "1-728-393-4241 x17099"
  },
  {
    "id": "PASSENGER-1032",
    "name": "Justin VonRueden",
    "phone": "1-777-931-9577 x84222"
  },
  {
    "id": "PASSENGER-6054",
    "name": "Cameron Pollich",
    "phone": "(569) 681-1247"
  },
  {
    "id": "PASSENGER-2509",
    "name": "Alyssa Ebert",
    "phone": "389.779.9689 x478"
  },
  {
    "id": "PASSENGER-5118",
    "name": "Frankie Rowe",
    "phone": "1-267-675-7347 x519"
  },
  {
    "id": "PASSENGER-1685",
    "name": "Don Senger",
    "phone": "1-329-740-8682"
  },
  {
    "id": "PASSENGER-1161",
    "name": "Trevor Heidenreich",
    "phone": "586.447.3746"
  },
  {
    "id": "PASSENGER-6870",
    "name": "Guy Koelpin",
    "phone": "390.339.0674 x6143"
  },
  {
    "id": "PASSENGER-5746",
    "name": "Lowell Murphy",
    "phone": "421.368.8657 x971"
  },
  {
    "id": "PASSENGER-6594",
    "name": "Myron Jerde",
    "phone": "855-356-5341 x247"
  },
  {
    "id": "PASSENGER-2366",
    "name": "Mario Little",
    "phone": "815-241-8847 x30087"
  },
  {
    "id": "PASSENGER-8051",
    "name": "Rolando Labadie",
    "phone": "1-754-221-2678 x75659"
  },
  {
    "id": "PASSENGER-4057",
    "name": "Clark Langworth",
    "phone": "1-218-903-5538 x8443"
  },
  {
    "id": "PASSENGER-8775",
    "name": "Camille Rath",
    "phone": "(800) 375-8186 x008"
  },
  {
    "id": "PASSENGER-1578",
    "name": "Derrick Beier",
    "phone": "856.337.5446 x54390"
  },
  {
    "id": "PASSENGER-1111",
    "name": "Darnell Gerhold DVM",
    "phone": "809-247-1674 x5017"
  },
  {
    "id": "PASSENGER-6011",
    "name": "Salvatore Jacobson",
    "phone": "814.782.8885 x967"
  },
  {
    "id": "PASSENGER-2333",
    "name": "Myrtle Flatley Jr.",
    "phone": "1-725-651-9390 x08329"
  },
  {
    "id": "PASSENGER-7291",
    "name": "Stanley Strosin",
    "phone": "1-612-323-1114 x19681"
  },
  {
    "id": "PASSENGER-1530",
    "name": "Mrs. Candice Cronin",
    "phone": "387.507.2743"
  },
  {
    "id": "PASSENGER-8089",
    "name": "Georgia Weber II",
    "phone": "725.542.2132"
  },
  {
    "id": "PASSENGER-5661",
    "name": "Eric Gerhold",
    "phone": "210.251.3915 x02513"
  },
  {
    "id": "PASSENGER-1611",
    "name": "Emilio Okuneva",
    "phone": "(564) 791-7911 x15602"
  },
  {
    "id": "PASSENGER-8757",
    "name": "Marc Raynor",
    "phone": "522.242.8439 x496"
  },
  {
    "id": "PASSENGER-2099",
    "name": "Phil McClure",
    "phone": "1-615-336-1132 x60022"
  },
  {
    "id": "PASSENGER-9271",
    "name": "George Roob",
    "phone": "(853) 372-9565 x1505"
  },
  {
    "id": "PASSENGER-7508",
    "name": "Herbert Cronin",
    "phone": "529.901.5975"
  },
  {
    "id": "PASSENGER-7927",
    "name": "Noah Mueller-Daniel",
    "phone": "597.852.1426 x5120"
  },
  {
    "id": "PASSENGER-1035",
    "name": "Cecelia Schumm",
    "phone": "1-685-868-6205 x612"
  },
  {
    "id": "PASSENGER-2312",
    "name": "Elisa Murphy",
    "phone": "471.641.9856 x6306"
  },
  {
    "id": "PASSENGER-2020",
    "name": "Douglas Wiza",
    "phone": "(804) 763-7288"
  },
  {
    "id": "PASSENGER-5130",
    "name": "Ms. Minnie Jaskolski",
    "phone": "411-848-3714"
  },
  {
    "id": "PASSENGER-9421",
    "name": "Juan Brakus",
    "phone": "1-527-830-0642"
  },
  {
    "id": "PASSENGER-2184",
    "name": "Bradley Bednar",
    "phone": "1-507-655-3102 x9842"
  },
  {
    "id": "PASSENGER-5204",
    "name": "Deborah Barton",
    "phone": "(896) 206-0615"
  },
  {
    "id": "PASSENGER-3031",
    "name": "Fannie Marvin",
    "phone": "(221) 913-4184 x247"
  },
  {
    "id": "PASSENGER-5607",
    "name": "Freda McLaughlin",
    "phone": "668-230-4452 x75301"
  },
  {
    "id": "PASSENGER-4697",
    "name": "Ms. Hope Bechtelar",
    "phone": "(622) 530-7063 x99469"
  },
  {
    "id": "PASSENGER-9691",
    "name": "Lee Cruickshank",
    "phone": "1-907-940-1991 x600"
  },
  {
    "id": "PASSENGER-8674",
    "name": "Randy Kovacek DVM",
    "phone": "464.986.1598 x292"
  },
  {
    "id": "PASSENGER-2575",
    "name": "Mrs. Marianne Stamm II",
    "phone": "261-961-1344 x32894"
  },
  {
    "id": "PASSENGER-5451",
    "name": "Nadine Cartwright",
    "phone": "(583) 507-2934 x7045"
  },
  {
    "id": "PASSENGER-2764",
    "name": "Dr. Brandon Harber",
    "phone": "(276) 603-2109 x2166"
  },
  {
    "id": "PASSENGER-7297",
    "name": "Sylvester Olson",
    "phone": "994.854.1707 x641"
  },
  {
    "id": "PASSENGER-6925",
    "name": "Lorenzo Greenfelder DVM",
    "phone": "(796) 744-2728 x529"
  },
  {
    "id": "PASSENGER-5940",
    "name": "Teri Olson III",
    "phone": "1-508-749-7155 x54547"
  },
  {
    "id": "PASSENGER-8124",
    "name": "Jenna Cummings",
    "phone": "324.863.4514 x2983"
  },
  {
    "id": "PASSENGER-7895",
    "name": "Ginger Champlin",
    "phone": "1-504-216-2982 x538"
  },
  {
    "id": "PASSENGER-4371",
    "name": "Brendan Windler III",
    "phone": "(525) 217-9874 x98383"
  },
  {
    "id": "PASSENGER-3372",
    "name": "Holly Kerluke",
    "phone": "820.745.8576 x758"
  },
  {
    "id": "PASSENGER-3349",
    "name": "Dr. Colleen Rice",
    "phone": "(860) 974-0892 x7493"
  },
  {
    "id": "PASSENGER-9097",
    "name": "Cesar Mueller III",
    "phone": "(889) 374-2823"
  },
  {
    "id": "PASSENGER-3737",
    "name": "Jeanette Schiller",
    "phone": "1-559-207-9213"
  },
  {
    "id": "PASSENGER-8175",
    "name": "Bradley Wolff",
    "phone": "1-811-526-4330 x1945"
  },
  {
    "id": "PASSENGER-6765",
    "name": "Erik Wolf DVM",
    "phone": "1-233-868-5370 x228"
  },
  {
    "id": "PASSENGER-9942",
    "name": "May Stark I",
    "phone": "(297) 883-0694 x081"
  },
  {
    "id": "PASSENGER-3688",
    "name": "Lance Doyle",
    "phone": "(241) 220-6553 x8999"
  },
  {
    "id": "PASSENGER-2233",
    "name": "Nichole Larson",
    "phone": "774-604-5976 x21022"
  },
  {
    "id": "PASSENGER-1160",
    "name": "Pedro Ledner",
    "phone": "342.861.3033 x9328"
  },
  {
    "id": "PASSENGER-8830",
    "name": "Elmer Dibbert",
    "phone": "225.245.1400 x89875"
  },
  {
    "id": "PASSENGER-8116",
    "name": "Terrence Gerhold",
    "phone": "1-327-509-1187 x138"
  },
  {
    "id": "PASSENGER-4138",
    "name": "Dr. Alton Abbott",
    "phone": "(646) 732-1823 x09863"
  },
  {
    "id": "PASSENGER-4594",
    "name": "Jerome Lang-Rohan",
    "phone": "347.211.5816 x931"
  },
  {
    "id": "PASSENGER-2463",
    "name": "Dana Klein",
    "phone": "827.991.2680"
  },
  {
    "id": "PASSENGER-2560",
    "name": "Ana Kautzer",
    "phone": "1-242-870-9520"
  },
  {
    "id": "PASSENGER-3599",
    "name": "Peggy Predovic",
    "phone": "479-218-2327 x0687"
  },
  {
    "id": "PASSENGER-2064",
    "name": "Brendan Runolfsdottir",
    "phone": "(232) 524-7588 x8372"
  },
  {
    "id": "PASSENGER-7646",
    "name": "Angel Tremblay",
    "phone": "1-841-856-2013 x77266"
  },
  {
    "id": "PASSENGER-5496",
    "name": "Melba Lynch",
    "phone": "847.524.4352 x972"
  },
  {
    "id": "PASSENGER-1033",
    "name": "Dr. Chris O'Conner",
    "phone": "414.492.3246 x730"
  },
  {
    "id": "PASSENGER-1751",
    "name": "Rachel Lakin",
    "phone": "(228) 526-0313 x99889"
  },
  {
    "id": "PASSENGER-6017",
    "name": "Tina Feeney DVM",
    "phone": "555.782.3883"
  },
  {
    "id": "PASSENGER-1459",
    "name": "Lance Ankunding",
    "phone": "716-878-4120 x9878"
  },
  {
    "id": "PASSENGER-6415",
    "name": "Charles Prohaska",
    "phone": "375.856.0248 x711"
  },
  {
    "id": "PASSENGER-2722",
    "name": "Ben Bayer",
    "phone": "(623) 404-8657 x17906"
  },
  {
    "id": "PASSENGER-6687",
    "name": "Cecelia Schumm",
    "phone": "1-809-969-3781 x6490"
  }
]