[
  {
    "id": "ROUTE-3247",
    "departureAirportId": "AIRPORT-LOS",
    "arrivalAirportId": "AIRPORT-CGH"
  },
  {
    "id": "ROUTE-9862",
    "departureAirportId": "AIRPORT-HKG",
    "arrivalAirportId": "AIRPORT-HNL"
  },
  {
    "id": "ROUTE-4906",
    "departureAirportId": "AIRPORT-HND",
    "arrivalAirportId": "AIRPORT-SSA"
  },
  {
    "id": "ROUTE-9215",
    "departureAirportId": "AIRPORT-BOG",
    "arrivalAirportId": "AIRPORT-NOU"
  },
  {
    "id": "ROUTE-3001",
    "departureAirportId": "AIRPORT-CLT",
    "arrivalAirportId": "AIRPORT-VCP"
  },
  {
    "id": "ROUTE-546",
    "departureAirportId": "AIRPORT-SCL",
    "arrivalAirportId": "AIRPORT-CMN"
  },
  {
    "id": "ROUTE-302",
    "departureAirportId": "AIRPORT-BCN",
    "arrivalAirportId": "AIRPORT-JNB"
  },
  {
    "id": "ROUTE-2979",
    "departureAirportId": "AIRPORT-POM",
    "arrivalAirportId": "AIRPORT-BCN"
  },
  {
    "id": "ROUTE-1860",
    "departureAirportId": "AIRPORT-BCN",
    "arrivalAirportId": "AIRPORT-WLG"
  },
  {
    "id": "ROUTE-9957",
    "departureAirportId": "AIRPORT-MEL",
    "arrivalAirportId": "AIRPORT-BOM"
  },
  {
    "id": "ROUTE-6608",
    "departureAirportId": "AIRPORT-SVO",
    "arrivalAirportId": "AIRPORT-BOM"
  },
  {
    "id": "ROUTE-2760",
    "departureAirportId": "AIRPORT-LAS",
    "arrivalAirportId": "AIRPORT-PEK"
  },
  {
    "id": "ROUTE-6287",
    "departureAirportId": "AIRPORT-PHX",
    "arrivalAirportId": "AIRPORT-JFK"
  },
  {
    "id": "ROUTE-4795",
    "departureAirportId": "AIRPORT-IAH",
    "arrivalAirportId": "AIRPORT-OGG"
  },
  {
    "id": "ROUTE-5036",
    "departureAirportId": "AIRPORT-MSP",
    "arrivalAirportId": "AIRPORT-MDE"
  },
  {
    "id": "ROUTE-4169",
    "departureAirportId": "AIRPORT-HBA",
    "arrivalAirportId": "AIRPORT-CWB"
  },
  {
    "id": "ROUTE-4551",
    "departureAirportId": "AIRPORT-POA",
    "arrivalAirportId": "AIRPORT-HRG"
  },
  {
    "id": "ROUTE-9066",
    "departureAirportId": "AIRPORT-YYZ",
    "arrivalAirportId": "AIRPORT-FCO"
  },
  {
    "id": "ROUTE-6113",
    "departureAirportId": "AIRPORT-LHR",
    "arrivalAirportId": "AIRPORT-NBO"
  },
  {
    "id": "ROUTE-6819",
    "departureAirportId": "AIRPORT-EZE",
    "arrivalAirportId": "AIRPORT-JFK"
  },
  {
    "id": "ROUTE-4243",
    "departureAirportId": "AIRPORT-WLG",
    "arrivalAirportId": "AIRPORT-HND"
  },
  {
    "id": "ROUTE-1228",
    "departureAirportId": "AIRPORT-SSA",
    "arrivalAirportId": "AIRPORT-TUN"
  },
  {
    "id": "ROUTE-3260",
    "departureAirportId": "AIRPORT-DUB",
    "arrivalAirportId": "AIRPORT-AKL"
  },
  {
    "id": "ROUTE-3803",
    "departureAirportId": "AIRPORT-DME",
    "arrivalAirportId": "AIRPORT-EZE"
  },
  {
    "id": "ROUTE-8071",
    "departureAirportId": "AIRPORT-CPT",
    "arrivalAirportId": "AIRPORT-SGN"
  },
  {
    "id": "ROUTE-6166",
    "departureAirportId": "AIRPORT-YYZ",
    "arrivalAirportId": "AIRPORT-VCP"
  },
  {
    "id": "ROUTE-9252",
    "departureAirportId": "AIRPORT-CMN",
    "arrivalAirportId": "AIRPORT-IST"
  },
  {
    "id": "ROUTE-5233",
    "departureAirportId": "AIRPORT-BCN",
    "arrivalAirportId": "AIRPORT-MDE"
  },
  {
    "id": "ROUTE-1133",
    "departureAirportId": "AIRPORT-BKK",
    "arrivalAirportId": "AIRPORT-BOM"
  },
  {
    "id": "ROUTE-8742",
    "departureAirportId": "AIRPORT-MDE",
    "arrivalAirportId": "AIRPORT-LHR"
  },
  {
    "id": "ROUTE-5599",
    "departureAirportId": "AIRPORT-EWR",
    "arrivalAirportId": "AIRPORT-SCL"
  },
  {
    "id": "ROUTE-4508",
    "departureAirportId": "AIRPORT-PPT",
    "arrivalAirportId": "AIRPORT-CNS"
  },
  {
    "id": "ROUTE-8719",
    "departureAirportId": "AIRPORT-CDG",
    "arrivalAirportId": "AIRPORT-GEA"
  },
  {
    "id": "ROUTE-1546",
    "departureAirportId": "AIRPORT-IAH",
    "arrivalAirportId": "AIRPORT-GEA"
  },
  {
    "id": "ROUTE-5142",
    "departureAirportId": "AIRPORT-ADL",
    "arrivalAirportId": "AIRPORT-HEL"
  },
  {
    "id": "ROUTE-3783",
    "departureAirportId": "AIRPORT-PHX",
    "arrivalAirportId": "AIRPORT-DMK"
  },
  {
    "id": "ROUTE-3505",
    "departureAirportId": "AIRPORT-CDG",
    "arrivalAirportId": "AIRPORT-HBA"
  },
  {
    "id": "ROUTE-4945",
    "departureAirportId": "AIRPORT-MIA",
    "arrivalAirportId": "AIRPORT-MDE"
  },
  {
    "id": "ROUTE-495",
    "departureAirportId": "AIRPORT-FOR",
    "arrivalAirportId": "AIRPORT-SZX"
  },
  {
    "id": "ROUTE-9424",
    "departureAirportId": "AIRPORT-LOS",
    "arrivalAirportId": "AIRPORT-ZRH"
  },
  {
    "id": "ROUTE-5624",
    "departureAirportId": "AIRPORT-OSL",
    "arrivalAirportId": "AIRPORT-PPT"
  },
  {
    "id": "ROUTE-4222",
    "departureAirportId": "AIRPORT-FRA",
    "arrivalAirportId": "AIRPORT-NAN"
  },
  {
    "id": "ROUTE-9392",
    "departureAirportId": "AIRPORT-CPT",
    "arrivalAirportId": "AIRPORT-ATH"
  },
  {
    "id": "ROUTE-9309",
    "departureAirportId": "AIRPORT-BSB",
    "arrivalAirportId": "AIRPORT-BOG"
  },
  {
    "id": "ROUTE-4936",
    "departureAirportId": "AIRPORT-SZX",
    "arrivalAirportId": "AIRPORT-LHR"
  },
  {
    "id": "ROUTE-9010",
    "departureAirportId": "AIRPORT-ARN",
    "arrivalAirportId": "AIRPORT-SFO"
  },
  {
    "id": "ROUTE-8311",
    "departureAirportId": "AIRPORT-XIY",
    "arrivalAirportId": "AIRPORT-FCO"
  },
  {
    "id": "ROUTE-3308",
    "departureAirportId": "AIRPORT-FOR",
    "arrivalAirportId": "AIRPORT-HKG"
  },
  {
    "id": "ROUTE-6866",
    "departureAirportId": "AIRPORT-BKK",
    "arrivalAirportId": "AIRPORT-PVG"
  },
  {
    "id": "ROUTE-5531",
    "departureAirportId": "AIRPORT-PHX",
    "arrivalAirportId": "AIRPORT-PEK"
  },
  {
    "id": "ROUTE-1661",
    "departureAirportId": "AIRPORT-LAX",
    "arrivalAirportId": "AIRPORT-SIN"
  },
  {
    "id": "ROUTE-7426",
    "departureAirportId": "AIRPORT-GRU",
    "arrivalAirportId": "AIRPORT-ATH"
  },
  {
    "id": "ROUTE-3988",
    "departureAirportId": "AIRPORT-TXL",
    "arrivalAirportId": "AIRPORT-PPT"
  },
  {
    "id": "ROUTE-5969",
    "departureAirportId": "AIRPORT-NRT",
    "arrivalAirportId": "AIRPORT-BOG"
  },
  {
    "id": "ROUTE-589",
    "departureAirportId": "AIRPORT-NAN",
    "arrivalAirportId": "AIRPORT-PHX"
  },
  {
    "id": "ROUTE-4441",
    "departureAirportId": "AIRPORT-JED",
    "arrivalAirportId": "AIRPORT-FOR"
  },
  {
    "id": "ROUTE-6276",
    "departureAirportId": "AIRPORT-CKG",
    "arrivalAirportId": "AIRPORT-ATL"
  },
  {
    "id": "ROUTE-1521",
    "departureAirportId": "AIRPORT-POA",
    "arrivalAirportId": "AIRPORT-SCL"
  },
  {
    "id": "ROUTE-6825",
    "departureAirportId": "AIRPORT-BSB",
    "arrivalAirportId": "AIRPORT-SFO"
  },
  {
    "id": "ROUTE-5965",
    "departureAirportId": "AIRPORT-CLO",
    "arrivalAirportId": "AIRPORT-DXB"
  },
  {
    "id": "ROUTE-6868",
    "departureAirportId": "AIRPORT-VCP",
    "arrivalAirportId": "AIRPORT-DXB"
  },
  {
    "id": "ROUTE-2410",
    "departureAirportId": "AIRPORT-PHX",
    "arrivalAirportId": "AIRPORT-ZIA"
  },
  {
    "id": "ROUTE-6145",
    "departureAirportId": "AIRPORT-SZX",
    "arrivalAirportId": "AIRPORT-MSP"
  },
  {
    "id": "ROUTE-2413",
    "departureAirportId": "AIRPORT-GRU",
    "arrivalAirportId": "AIRPORT-ICN"
  },
  {
    "id": "ROUTE-3722",
    "departureAirportId": "AIRPORT-SHA",
    "arrivalAirportId": "AIRPORT-NBO"
  },
  {
    "id": "ROUTE-4911",
    "departureAirportId": "AIRPORT-CBR",
    "arrivalAirportId": "AIRPORT-CDG"
  },
  {
    "id": "ROUTE-8791",
    "departureAirportId": "AIRPORT-CNS",
    "arrivalAirportId": "AIRPORT-OOL"
  },
  {
    "id": "ROUTE-5664",
    "departureAirportId": "AIRPORT-NBO",
    "arrivalAirportId": "AIRPORT-ARN"
  },
  {
    "id": "ROUTE-895",
    "departureAirportId": "AIRPORT-MIA",
    "arrivalAirportId": "AIRPORT-CWB"
  },
  {
    "id": "ROUTE-6225",
    "departureAirportId": "AIRPORT-SSA",
    "arrivalAirportId": "AIRPORT-PPT"
  },
  {
    "id": "ROUTE-9868",
    "departureAirportId": "AIRPORT-MIA",
    "arrivalAirportId": "AIRPORT-OOL"
  },
  {
    "id": "ROUTE-6493",
    "departureAirportId": "AIRPORT-CBR",
    "arrivalAirportId": "AIRPORT-VIE"
  },
  {
    "id": "ROUTE-6738",
    "departureAirportId": "AIRPORT-EZE",
    "arrivalAirportId": "AIRPORT-ORD"
  },
  {
    "id": "ROUTE-6822",
    "departureAirportId": "AIRPORT-SSA",
    "arrivalAirportId": "AIRPORT-DFW"
  },
  {
    "id": "ROUTE-9403",
    "departureAirportId": "AIRPORT-DMK",
    "arrivalAirportId": "AIRPORT-PEK"
  },
  {
    "id": "ROUTE-4367",
    "departureAirportId": "AIRPORT-SIN",
    "arrivalAirportId": "AIRPORT-ATL"
  },
  {
    "id": "ROUTE-6499",
    "departureAirportId": "AIRPORT-NOU",
    "arrivalAirportId": "AIRPORT-SDU"
  },
  {
    "id": "ROUTE-5904",
    "departureAirportId": "AIRPORT-FCO",
    "arrivalAirportId": "AIRPORT-IAH"
  },
  {
    "id": "ROUTE-9623",
    "departureAirportId": "AIRPORT-ORD",
    "arrivalAirportId": "AIRPORT-MDE"
  },
  {
    "id": "ROUTE-5602",
    "departureAirportId": "AIRPORT-CMN",
    "arrivalAirportId": "AIRPORT-BOG"
  },
  {
    "id": "ROUTE-3712",
    "departureAirportId": "AIRPORT-BOM",
    "arrivalAirportId": "AIRPORT-DEL"
  },
  {
    "id": "ROUTE-8718",
    "departureAirportId": "AIRPORT-DEL",
    "arrivalAirportId": "AIRPORT-DUB"
  },
  {
    "id": "ROUTE-8876",
    "departureAirportId": "AIRPORT-ZIA",
    "arrivalAirportId": "AIRPORT-TXL"
  },
  {
    "id": "ROUTE-342",
    "departureAirportId": "AIRPORT-PER",
    "arrivalAirportId": "AIRPORT-CWB"
  },
  {
    "id": "ROUTE-2147",
    "departureAirportId": "AIRPORT-ADD",
    "arrivalAirportId": "AIRPORT-SIN"
  },
  {
    "id": "ROUTE-7909",
    "departureAirportId": "AIRPORT-FCO",
    "arrivalAirportId": "AIRPORT-DMK"
  },
  {
    "id": "ROUTE-5513",
    "departureAirportId": "AIRPORT-LAS",
    "arrivalAirportId": "AIRPORT-CPT"
  },
  {
    "id": "ROUTE-543",
    "departureAirportId": "AIRPORT-OOL",
    "arrivalAirportId": "AIRPORT-SHA"
  },
  {
    "id": "ROUTE-3148",
    "departureAirportId": "AIRPORT-CWB",
    "arrivalAirportId": "AIRPORT-ZRH"
  },
  {
    "id": "ROUTE-2787",
    "departureAirportId": "AIRPORT-SIN",
    "arrivalAirportId": "AIRPORT-MAD"
  },
  {
    "id": "ROUTE-7632",
    "departureAirportId": "AIRPORT-EWR",
    "arrivalAirportId": "AIRPORT-HEL"
  },
  {
    "id": "ROUTE-2672",
    "departureAirportId": "AIRPORT-XIY",
    "arrivalAirportId": "AIRPORT-CKG"
  },
  {
    "id": "ROUTE-7579",
    "departureAirportId": "AIRPORT-DMK",
    "arrivalAirportId": "AIRPORT-REC"
  },
  {
    "id": "ROUTE-5129",
    "departureAirportId": "AIRPORT-CTU",
    "arrivalAirportId": "AIRPORT-HBA"
  },
  {
    "id": "ROUTE-6700",
    "departureAirportId": "AIRPORT-CGK",
    "arrivalAirportId": "AIRPORT-CDG"
  },
  {
    "id": "ROUTE-1543",
    "departureAirportId": "AIRPORT-OSL",
    "arrivalAirportId": "AIRPORT-BSB"
  },
  {
    "id": "ROUTE-1346",
    "departureAirportId": "AIRPORT-BSB",
    "arrivalAirportId": "AIRPORT-MSP"
  },
  {
    "id": "ROUTE-3663",
    "departureAirportId": "AIRPORT-JFK",
    "arrivalAirportId": "AIRPORT-EZE"
  },
  {
    "id": "ROUTE-7676",
    "departureAirportId": "AIRPORT-SHA",
    "arrivalAirportId": "AIRPORT-SDU"
  },
  {
    "id": "ROUTE-4193",
    "departureAirportId": "AIRPORT-SEA",
    "arrivalAirportId": "AIRPORT-ADL"
  }
]